[
  {
    "recordingId": "23846e2d-ce0f-438b-8ee4-eebf5e4e076b",
    "page": "113",
    "bookSlug": "sh-1991",
    "url": "https://corksacredharp.bandcamp.com/track/113-the-prodigal-son-5",
    "embedUrl": "https://corksacredharp.bandcamp.com/track/113-the-prodigal-son-5",
    "status": "CONFIRMED"
  },
  {
    "recordingId": "23846e2d-ce0f-438b-8ee4-eebf5e4e076b",
    "page": "29t",
    "bookSlug": "sh-1991",
    "url": "https://corksacredharp.bandcamp.com/track/29t-fairfield-7",
    "embedUrl": "https://corksacredharp.bandcamp.com/track/29t-fairfield-7",
    "status": "CONFIRMED"
  },
  {
    "recordingId": "23846e2d-ce0f-438b-8ee4-eebf5e4e076b",
    "page": "283",
    "bookSlug": "sh-1991",
    "url": "https://corksacredharp.bandcamp.com/track/283-sabbath-morning-6",
    "embedUrl": "https://corksacredharp.bandcamp.com/track/283-sabbath-morning-6",
    "status": "CONFIRMED"
  },
  {
    "recordingId": "23846e2d-ce0f-438b-8ee4-eebf5e4e076b",
    "page": "328",
    "bookSlug": "sh-1991",
    "url": "https://corksacredharp.bandcamp.com/track/328-praise-god-6",
    "embedUrl": "https://corksacredharp.bandcamp.com/track/328-praise-god-6",
    "status": "CONFIRMED"
  },
  {
    "recordingId": "23846e2d-ce0f-438b-8ee4-eebf5e4e076b",
    "page": "430",
    "bookSlug": "sh-1991",
    "url": "https://corksacredharp.bandcamp.com/track/430-arbacoochee-8",
    "embedUrl": "https://corksacredharp.bandcamp.com/track/430-arbacoochee-8",
    "status": "CONFIRMED"
  },
  {
    "recordingId": "23846e2d-ce0f-438b-8ee4-eebf5e4e076b",
    "page": "352",
    "bookSlug": "sh-1991",
    "url": "https://corksacredharp.bandcamp.com/track/352-swanton-3",
    "embedUrl": "https://corksacredharp.bandcamp.com/track/352-swanton-3",
    "status": "CONFIRMED"
  },
  {
    "recordingId": "23846e2d-ce0f-438b-8ee4-eebf5e4e076b",
    "page": "350",
    "bookSlug": "sh-1991",
    "url": "https://corksacredharp.bandcamp.com/track/350-nativity-4",
    "embedUrl": "https://corksacredharp.bandcamp.com/track/350-nativity-4",
    "status": "CONFIRMED"
  },
  {
    "recordingId": "23846e2d-ce0f-438b-8ee4-eebf5e4e076b",
    "page": "332",
    "bookSlug": "sh-1991",
    "url": "https://corksacredharp.bandcamp.com/track/332-sons-of-sorrow-3",
    "embedUrl": "https://corksacredharp.bandcamp.com/track/332-sons-of-sorrow-3",
    "status": "CONFIRMED"
  },
  {
    "recordingId": "23846e2d-ce0f-438b-8ee4-eebf5e4e076b",
    "page": "383",
    "bookSlug": "sh-1991",
    "url": "https://corksacredharp.bandcamp.com/track/383-eternal-day-8",
    "embedUrl": "https://corksacredharp.bandcamp.com/track/383-eternal-day-8",
    "status": "CONFIRMED"
  },
  {
    "recordingId": "23846e2d-ce0f-438b-8ee4-eebf5e4e076b",
    "page": "370",
    "bookSlug": "sh-1991",
    "url": "https://corksacredharp.bandcamp.com/track/370-monroe",
    "embedUrl": "https://corksacredharp.bandcamp.com/track/370-monroe",
    "status": "CONFIRMED"
  },
  {
    "recordingId": "23846e2d-ce0f-438b-8ee4-eebf5e4e076b",
    "page": "474",
    "bookSlug": "sh-1991",
    "url": "https://corksacredharp.bandcamp.com/track/474-mount-desert-7",
    "embedUrl": "https://corksacredharp.bandcamp.com/track/474-mount-desert-7",
    "status": "CONFIRMED"
  },
  {
    "recordingId": "23846e2d-ce0f-438b-8ee4-eebf5e4e076b",
    "page": "373",
    "bookSlug": "sh-1991",
    "url": "https://corksacredharp.bandcamp.com/track/373-homeward-bound-3",
    "embedUrl": "https://corksacredharp.bandcamp.com/track/373-homeward-bound-3",
    "status": "CONFIRMED"
  },
  {
    "recordingId": "23846e2d-ce0f-438b-8ee4-eebf5e4e076b",
    "page": "150",
    "bookSlug": "sh-1991",
    "url": "https://corksacredharp.bandcamp.com/track/150-amity",
    "embedUrl": "https://corksacredharp.bandcamp.com/track/150-amity",
    "status": "CONFIRMED"
  },
  {
    "recordingId": "23846e2d-ce0f-438b-8ee4-eebf5e4e076b",
    "page": "276",
    "bookSlug": "sh-1991",
    "url": "https://corksacredharp.bandcamp.com/track/276-bridgewater-9",
    "embedUrl": "https://corksacredharp.bandcamp.com/track/276-bridgewater-9",
    "status": "CONFIRMED"
  },
  {
    "recordingId": "23846e2d-ce0f-438b-8ee4-eebf5e4e076b",
    "page": "282",
    "bookSlug": "sh-1991",
    "url": "https://corksacredharp.bandcamp.com/track/282-im-going-home-4",
    "embedUrl": "https://corksacredharp.bandcamp.com/track/282-im-going-home-4",
    "status": "CONFIRMED"
  },
  {
    "recordingId": "23846e2d-ce0f-438b-8ee4-eebf5e4e076b",
    "page": "468",
    "bookSlug": "sh-1991",
    "url": "https://corksacredharp.bandcamp.com/track/468-bristol-2",
    "embedUrl": "https://corksacredharp.bandcamp.com/track/468-bristol-2",
    "status": "CONFIRMED"
  },
  {
    "recordingId": "23846e2d-ce0f-438b-8ee4-eebf5e4e076b",
    "page": "527",
    "bookSlug": "sh-1991",
    "url": "https://corksacredharp.bandcamp.com/track/527-my-life-and-breath",
    "embedUrl": "https://corksacredharp.bandcamp.com/track/527-my-life-and-breath",
    "status": "CONFIRMED"
  },
  {
    "recordingId": "23846e2d-ce0f-438b-8ee4-eebf5e4e076b",
    "page": "396",
    "bookSlug": "sh-1991",
    "url": "https://corksacredharp.bandcamp.com/track/396-notes-almost-divine-4",
    "embedUrl": "https://corksacredharp.bandcamp.com/track/396-notes-almost-divine-4",
    "status": "CONFIRMED"
  },
  {
    "recordingId": "23846e2d-ce0f-438b-8ee4-eebf5e4e076b",
    "page": "186",
    "bookSlug": "sh-1991",
    "url": "https://corksacredharp.bandcamp.com/track/186-sherburne-5",
    "embedUrl": "https://corksacredharp.bandcamp.com/track/186-sherburne-5",
    "status": "CONFIRMED"
  },
  {
    "recordingId": "23846e2d-ce0f-438b-8ee4-eebf5e4e076b",
    "page": "192",
    "bookSlug": "sh-1991",
    "url": "https://corksacredharp.bandcamp.com/track/192-schenectady-9",
    "embedUrl": "https://corksacredharp.bandcamp.com/track/192-schenectady-9",
    "status": "CONFIRMED"
  },
  {
    "recordingId": "23846e2d-ce0f-438b-8ee4-eebf5e4e076b",
    "page": "455",
    "bookSlug": "sh-1991",
    "url": "https://corksacredharp.bandcamp.com/track/455-soar-away-5",
    "embedUrl": "https://corksacredharp.bandcamp.com/track/455-soar-away-5",
    "status": "CONFIRMED"
  },
  {
    "recordingId": "23846e2d-ce0f-438b-8ee4-eebf5e4e076b",
    "page": "411",
    "bookSlug": "sh-1991",
    "url": "https://corksacredharp.bandcamp.com/track/411-morning-prayer-6",
    "embedUrl": "https://corksacredharp.bandcamp.com/track/411-morning-prayer-6",
    "status": "CONFIRMED"
  },
  {
    "recordingId": "23846e2d-ce0f-438b-8ee4-eebf5e4e076b",
    "page": "34b",
    "bookSlug": "sh-1991",
    "url": "https://corksacredharp.bandcamp.com/track/34b-st-thomas-4",
    "embedUrl": "https://corksacredharp.bandcamp.com/track/34b-st-thomas-4",
    "status": "CONFIRMED"
  },
  {
    "recordingId": "23846e2d-ce0f-438b-8ee4-eebf5e4e076b",
    "page": "499",
    "bookSlug": "sh-1991",
    "url": "https://corksacredharp.bandcamp.com/track/499-at-rest",
    "embedUrl": "https://corksacredharp.bandcamp.com/track/499-at-rest",
    "status": "CONFIRMED"
  },
  {
    "recordingId": "23846e2d-ce0f-438b-8ee4-eebf5e4e076b",
    "page": "69t",
    "bookSlug": "sh-1991",
    "url": "https://corksacredharp.bandcamp.com/track/69t-ministers-farewell-3",
    "embedUrl": "https://corksacredharp.bandcamp.com/track/69t-ministers-farewell-3",
    "status": "CONFIRMED"
  },
  {
    "recordingId": "23846e2d-ce0f-438b-8ee4-eebf5e4e076b",
    "page": "498",
    "bookSlug": "sh-1991",
    "url": "https://corksacredharp.bandcamp.com/track/498-the-resurrection-day-4",
    "embedUrl": "https://corksacredharp.bandcamp.com/track/498-the-resurrection-day-4",
    "status": "CONFIRMED"
  },
  {
    "recordingId": "23846e2d-ce0f-438b-8ee4-eebf5e4e076b",
    "page": "155",
    "bookSlug": "sh-1991",
    "url": "https://corksacredharp.bandcamp.com/track/155-northfield-6",
    "embedUrl": "https://corksacredharp.bandcamp.com/track/155-northfield-6",
    "status": "CONFIRMED"
  },
  {
    "recordingId": "23846e2d-ce0f-438b-8ee4-eebf5e4e076b",
    "page": "382",
    "bookSlug": "sh-1991",
    "url": "https://corksacredharp.bandcamp.com/track/382-coston",
    "embedUrl": "https://corksacredharp.bandcamp.com/track/382-coston",
    "status": "CONFIRMED"
  },
  {
    "recordingId": "23846e2d-ce0f-438b-8ee4-eebf5e4e076b",
    "page": "53",
    "bookSlug": "sh-1991",
    "url": "https://corksacredharp.bandcamp.com/track/53-jerusalem-4",
    "embedUrl": "https://corksacredharp.bandcamp.com/track/53-jerusalem-4",
    "status": "CONFIRMED"
  },
  {
    "recordingId": "23846e2d-ce0f-438b-8ee4-eebf5e4e076b",
    "page": "97",
    "bookSlug": "sh-1991",
    "url": "https://corksacredharp.bandcamp.com/track/97-well-soon-be-there-2",
    "embedUrl": "https://corksacredharp.bandcamp.com/track/97-well-soon-be-there-2",
    "status": "CONFIRMED"
  },
  {
    "recordingId": "23846e2d-ce0f-438b-8ee4-eebf5e4e076b",
    "page": "269",
    "bookSlug": "sh-1991",
    "url": "https://corksacredharp.bandcamp.com/track/269-bear-creek-7",
    "embedUrl": "https://corksacredharp.bandcamp.com/track/269-bear-creek-7",
    "status": "CONFIRMED"
  },
  {
    "recordingId": "23846e2d-ce0f-438b-8ee4-eebf5e4e076b",
    "page": "98",
    "bookSlug": "sh-1991",
    "url": "https://corksacredharp.bandcamp.com/track/98-dull-care",
    "embedUrl": "https://corksacredharp.bandcamp.com/track/98-dull-care",
    "status": "CONFIRMED"
  },
  {
    "recordingId": "23846e2d-ce0f-438b-8ee4-eebf5e4e076b",
    "page": "384",
    "bookSlug": "sh-1991",
    "url": "https://corksacredharp.bandcamp.com/track/384-panting-for-heaven-6",
    "embedUrl": "https://corksacredharp.bandcamp.com/track/384-panting-for-heaven-6",
    "status": "CONFIRMED"
  },
  {
    "recordingId": "23846e2d-ce0f-438b-8ee4-eebf5e4e076b",
    "page": "36b",
    "bookSlug": "sh-1991",
    "url": "https://corksacredharp.bandcamp.com/track/36b-ninety-fifth-4",
    "embedUrl": "https://corksacredharp.bandcamp.com/track/36b-ninety-fifth-4",
    "status": "CONFIRMED"
  },
  {
    "recordingId": "23846e2d-ce0f-438b-8ee4-eebf5e4e076b",
    "page": "212",
    "bookSlug": "sh-1991",
    "url": "https://corksacredharp.bandcamp.com/track/212-sharon-5",
    "embedUrl": "https://corksacredharp.bandcamp.com/track/212-sharon-5",
    "status": "CONFIRMED"
  },
  {
    "recordingId": "23846e2d-ce0f-438b-8ee4-eebf5e4e076b",
    "page": "142",
    "bookSlug": "sh-1991",
    "url": "https://corksacredharp.bandcamp.com/track/142-stratfield-7",
    "embedUrl": "https://corksacredharp.bandcamp.com/track/142-stratfield-7",
    "status": "CONFIRMED"
  },
  {
    "recordingId": "23846e2d-ce0f-438b-8ee4-eebf5e4e076b",
    "page": "148",
    "bookSlug": "sh-1991",
    "url": "https://corksacredharp.bandcamp.com/track/148-jefferson-8",
    "embedUrl": "https://corksacredharp.bandcamp.com/track/148-jefferson-8",
    "status": "CONFIRMED"
  },
  {
    "recordingId": "23846e2d-ce0f-438b-8ee4-eebf5e4e076b",
    "page": "68b",
    "bookSlug": "sh-1991",
    "url": "https://corksacredharp.bandcamp.com/track/68b-ortonville-5",
    "embedUrl": "https://corksacredharp.bandcamp.com/track/68b-ortonville-5",
    "status": "CONFIRMED"
  },
  {
    "recordingId": "23846e2d-ce0f-438b-8ee4-eebf5e4e076b",
    "page": "347",
    "bookSlug": "sh-1991",
    "url": "https://corksacredharp.bandcamp.com/track/347-christians-farewell-5",
    "embedUrl": "https://corksacredharp.bandcamp.com/track/347-christians-farewell-5",
    "status": "CONFIRMED"
  },
  {
    "recordingId": "23846e2d-ce0f-438b-8ee4-eebf5e4e076b",
    "page": "495",
    "bookSlug": "sh-1991",
    "url": "https://corksacredharp.bandcamp.com/track/495-the-midnight-cry-3",
    "embedUrl": "https://corksacredharp.bandcamp.com/track/495-the-midnight-cry-3",
    "status": "CONFIRMED"
  },
  {
    "recordingId": "23846e2d-ce0f-438b-8ee4-eebf5e4e076b",
    "page": "419",
    "bookSlug": "sh-1991",
    "url": "https://corksacredharp.bandcamp.com/track/419-melancholy-day-4",
    "embedUrl": "https://corksacredharp.bandcamp.com/track/419-melancholy-day-4",
    "status": "CONFIRMED"
  },
  {
    "recordingId": "23846e2d-ce0f-438b-8ee4-eebf5e4e076b",
    "page": "522",
    "bookSlug": "sh-1991",
    "url": "https://corksacredharp.bandcamp.com/track/522-ye-heedless-ones-6",
    "embedUrl": "https://corksacredharp.bandcamp.com/track/522-ye-heedless-ones-6",
    "status": "CONFIRMED"
  },
  {
    "recordingId": "23846e2d-ce0f-438b-8ee4-eebf5e4e076b",
    "page": "564",
    "bookSlug": "sh-1991",
    "url": "https://corksacredharp.bandcamp.com/track/564-zion-4",
    "embedUrl": "https://corksacredharp.bandcamp.com/track/564-zion-4",
    "status": "CONFIRMED"
  },
  {
    "recordingId": "23846e2d-ce0f-438b-8ee4-eebf5e4e076b",
    "page": "201",
    "bookSlug": "sh-1991",
    "url": "https://corksacredharp.bandcamp.com/track/201-pilgrim-5",
    "embedUrl": "https://corksacredharp.bandcamp.com/track/201-pilgrim-5",
    "status": "CONFIRMED"
  },
  {
    "recordingId": "23846e2d-ce0f-438b-8ee4-eebf5e4e076b",
    "page": "32b",
    "bookSlug": "sh-1991",
    "url": "https://corksacredharp.bandcamp.com/track/32b-distress",
    "embedUrl": "https://corksacredharp.bandcamp.com/track/32b-distress",
    "status": "CONFIRMED"
  },
  {
    "recordingId": "23846e2d-ce0f-438b-8ee4-eebf5e4e076b",
    "page": "172",
    "bookSlug": "sh-1991",
    "url": "https://corksacredharp.bandcamp.com/track/172-harmony-4",
    "embedUrl": "https://corksacredharp.bandcamp.com/track/172-harmony-4",
    "status": "CONFIRMED"
  },
  {
    "recordingId": "23846e2d-ce0f-438b-8ee4-eebf5e4e076b",
    "page": "92",
    "bookSlug": "sh-1991",
    "url": "https://corksacredharp.bandcamp.com/track/92-burk",
    "embedUrl": "https://corksacredharp.bandcamp.com/track/92-burk",
    "status": "CONFIRMED"
  },
  {
    "recordingId": "23846e2d-ce0f-438b-8ee4-eebf5e4e076b",
    "page": "425",
    "bookSlug": "sh-1991",
    "url": "https://corksacredharp.bandcamp.com/track/425-golden-streets-6",
    "embedUrl": "https://corksacredharp.bandcamp.com/track/425-golden-streets-6",
    "status": "CONFIRMED"
  },
  {
    "recordingId": "23846e2d-ce0f-438b-8ee4-eebf5e4e076b",
    "page": "189",
    "bookSlug": "sh-1991",
    "url": "https://corksacredharp.bandcamp.com/track/189-montgomery-6",
    "embedUrl": "https://corksacredharp.bandcamp.com/track/189-montgomery-6",
    "status": "CONFIRMED"
  },
  {
    "recordingId": "23846e2d-ce0f-438b-8ee4-eebf5e4e076b",
    "page": "236",
    "bookSlug": "sh-1991",
    "url": "https://corksacredharp.bandcamp.com/track/236-easter-anthem-7",
    "embedUrl": "https://corksacredharp.bandcamp.com/track/236-easter-anthem-7",
    "status": "CONFIRMED"
  },
  {
    "recordingId": "23846e2d-ce0f-438b-8ee4-eebf5e4e076b",
    "page": "460",
    "bookSlug": "sh-1991",
    "url": "https://corksacredharp.bandcamp.com/track/460-sardis-6",
    "embedUrl": "https://corksacredharp.bandcamp.com/track/460-sardis-6",
    "status": "CONFIRMED"
  },
  {
    "recordingId": "23846e2d-ce0f-438b-8ee4-eebf5e4e076b",
    "page": "49b",
    "bookSlug": "sh-1991",
    "url": "https://corksacredharp.bandcamp.com/track/49b-mear-10",
    "embedUrl": "https://corksacredharp.bandcamp.com/track/49b-mear-10",
    "status": "CONFIRMED"
  },
  {
    "recordingId": "23846e2d-ce0f-438b-8ee4-eebf5e4e076b",
    "page": "371",
    "bookSlug": "sh-1991",
    "url": "https://corksacredharp.bandcamp.com/track/371-heavenly-dove",
    "embedUrl": "https://corksacredharp.bandcamp.com/track/371-heavenly-dove",
    "status": "CONFIRMED"
  },
  {
    "recordingId": "23846e2d-ce0f-438b-8ee4-eebf5e4e076b",
    "page": "176t",
    "bookSlug": "sh-1991",
    "url": "https://corksacredharp.bandcamp.com/track/176t-ragan-4",
    "embedUrl": "https://corksacredharp.bandcamp.com/track/176t-ragan-4",
    "status": "CONFIRMED"
  },
  {
    "recordingId": "23846e2d-ce0f-438b-8ee4-eebf5e4e076b",
    "page": "107",
    "bookSlug": "sh-1991",
    "url": "https://corksacredharp.bandcamp.com/track/107-russia-7",
    "embedUrl": "https://corksacredharp.bandcamp.com/track/107-russia-7",
    "status": "CONFIRMED"
  },
  {
    "recordingId": "23846e2d-ce0f-438b-8ee4-eebf5e4e076b",
    "page": "573",
    "bookSlug": "sh-1991",
    "url": "https://corksacredharp.bandcamp.com/track/573-harpeth-valley-3",
    "embedUrl": "https://corksacredharp.bandcamp.com/track/573-harpeth-valley-3",
    "status": "CONFIRMED"
  },
  {
    "recordingId": "23846e2d-ce0f-438b-8ee4-eebf5e4e076b",
    "page": "30b",
    "bookSlug": "sh-1991",
    "url": "https://corksacredharp.bandcamp.com/track/30b-prospect-7",
    "embedUrl": "https://corksacredharp.bandcamp.com/track/30b-prospect-7",
    "status": "CONFIRMED"
  },
  {
    "recordingId": "23846e2d-ce0f-438b-8ee4-eebf5e4e076b",
    "page": "501",
    "bookSlug": "sh-1991",
    "url": "https://corksacredharp.bandcamp.com/track/501-oleary-4",
    "embedUrl": "https://corksacredharp.bandcamp.com/track/501-oleary-4",
    "status": "CONFIRMED"
  },
  {
    "recordingId": "23846e2d-ce0f-438b-8ee4-eebf5e4e076b",
    "page": "315",
    "bookSlug": "sh-1991",
    "url": "https://corksacredharp.bandcamp.com/track/315-immensity-3",
    "embedUrl": "https://corksacredharp.bandcamp.com/track/315-immensity-3",
    "status": "CONFIRMED"
  },
  {
    "recordingId": "23846e2d-ce0f-438b-8ee4-eebf5e4e076b",
    "page": "102",
    "bookSlug": "sh-1991",
    "url": "https://corksacredharp.bandcamp.com/track/102-fulfillment-6",
    "embedUrl": "https://corksacredharp.bandcamp.com/track/102-fulfillment-6",
    "status": "CONFIRMED"
  },
  {
    "recordingId": "23846e2d-ce0f-438b-8ee4-eebf5e4e076b",
    "page": "340",
    "bookSlug": "sh-1991",
    "url": "https://corksacredharp.bandcamp.com/track/340-odem-second-3",
    "embedUrl": "https://corksacredharp.bandcamp.com/track/340-odem-second-3",
    "status": "CONFIRMED"
  },
  {
    "recordingId": "23846e2d-ce0f-438b-8ee4-eebf5e4e076b",
    "page": "361",
    "bookSlug": "sh-1991",
    "url": "https://corksacredharp.bandcamp.com/track/361-loving-jesus-3",
    "embedUrl": "https://corksacredharp.bandcamp.com/track/361-loving-jesus-3",
    "status": "CONFIRMED"
  },
  {
    "recordingId": "23846e2d-ce0f-438b-8ee4-eebf5e4e076b",
    "page": "440",
    "bookSlug": "sh-1991",
    "url": "https://corksacredharp.bandcamp.com/track/440-north-salem-7",
    "embedUrl": "https://corksacredharp.bandcamp.com/track/440-north-salem-7",
    "status": "CONFIRMED"
  },
  {
    "recordingId": "23846e2d-ce0f-438b-8ee4-eebf5e4e076b",
    "page": "160b",
    "bookSlug": "sh-1991",
    "url": "https://corksacredharp.bandcamp.com/track/160b-turn-sinner-turn",
    "embedUrl": "https://corksacredharp.bandcamp.com/track/160b-turn-sinner-turn",
    "status": "CONFIRMED"
  },
  {
    "recordingId": "23846e2d-ce0f-438b-8ee4-eebf5e4e076b",
    "page": "168",
    "bookSlug": "sh-1991",
    "url": "https://corksacredharp.bandcamp.com/track/168-cowper-7",
    "embedUrl": "https://corksacredharp.bandcamp.com/track/168-cowper-7",
    "status": "CONFIRMED"
  },
  {
    "recordingId": "23846e2d-ce0f-438b-8ee4-eebf5e4e076b",
    "page": "121",
    "bookSlug": "sh-1991",
    "url": "https://corksacredharp.bandcamp.com/track/121-florence-4",
    "embedUrl": "https://corksacredharp.bandcamp.com/track/121-florence-4",
    "status": "CONFIRMED"
  },
  {
    "recordingId": "23846e2d-ce0f-438b-8ee4-eebf5e4e076b",
    "page": "549",
    "bookSlug": "sh-1991",
    "url": "https://corksacredharp.bandcamp.com/track/549-phillips-farewell",
    "embedUrl": "https://corksacredharp.bandcamp.com/track/549-phillips-farewell",
    "status": "CONFIRMED"
  },
  {
    "recordingId": "23846e2d-ce0f-438b-8ee4-eebf5e4e076b",
    "page": "36t",
    "bookSlug": "sh-1991",
    "url": "https://corksacredharp.bandcamp.com/track/36t-america-3",
    "embedUrl": "https://corksacredharp.bandcamp.com/track/36t-america-3",
    "status": "CONFIRMED"
  },
  {
    "recordingId": "23846e2d-ce0f-438b-8ee4-eebf5e4e076b",
    "page": "63",
    "bookSlug": "sh-1991",
    "url": "https://corksacredharp.bandcamp.com/track/63-coronation-5",
    "embedUrl": "https://corksacredharp.bandcamp.com/track/63-coronation-5",
    "status": "CONFIRMED"
  },
  {
    "recordingId": "23846e2d-ce0f-438b-8ee4-eebf5e4e076b",
    "page": "542",
    "bookSlug": "sh-1991",
    "url": "https://corksacredharp.bandcamp.com/track/542-ill-seek-his-blessings-9",
    "embedUrl": "https://corksacredharp.bandcamp.com/track/542-ill-seek-his-blessings-9",
    "status": "CONFIRMED"
  },
  {
    "recordingId": "23846e2d-ce0f-438b-8ee4-eebf5e4e076b",
    "page": "319",
    "bookSlug": "sh-1991",
    "url": "https://corksacredharp.bandcamp.com/track/319-religion-is-a-fortune-6",
    "embedUrl": "https://corksacredharp.bandcamp.com/track/319-religion-is-a-fortune-6",
    "status": "CONFIRMED"
  },
  {
    "recordingId": "23846e2d-ce0f-438b-8ee4-eebf5e4e076b",
    "page": "348t",
    "bookSlug": "sh-1991",
    "url": "https://corksacredharp.bandcamp.com/track/348t-ainslie-6",
    "embedUrl": "https://corksacredharp.bandcamp.com/track/348t-ainslie-6",
    "status": "CONFIRMED"
  },
  {
    "recordingId": "23846e2d-ce0f-438b-8ee4-eebf5e4e076b",
    "page": "146",
    "bookSlug": "sh-1991",
    "url": "https://corksacredharp.bandcamp.com/track/146-hallelujah-7",
    "embedUrl": "https://corksacredharp.bandcamp.com/track/146-hallelujah-7",
    "status": "CONFIRMED"
  }
]