[
  {
    "recordingId": "395bfbbb-4b52-49bd-b7b1-9c20c3b8aaf2",
    "page": "72b",
    "bookSlug": "sh-1991",
    "url": "https://corksacredharp.bandcamp.com/track/72b-bellevue-4",
    "embedUrl": "https://corksacredharp.bandcamp.com/track/72b-bellevue-4",
    "status": "CONFIRMED"
  },
  {
    "recordingId": "395bfbbb-4b52-49bd-b7b1-9c20c3b8aaf2",
    "page": "47t",
    "bookSlug": "sh-1991",
    "url": "https://corksacredharp.bandcamp.com/track/47t-primrose-6",
    "embedUrl": "https://corksacredharp.bandcamp.com/track/47t-primrose-6",
    "status": "CONFIRMED"
  },
  {
    "recordingId": "395bfbbb-4b52-49bd-b7b1-9c20c3b8aaf2",
    "page": "56b",
    "bookSlug": "sh-1991",
    "url": "https://corksacredharp.bandcamp.com/track/56b-villulia-6",
    "embedUrl": "https://corksacredharp.bandcamp.com/track/56b-villulia-6",
    "status": "CONFIRMED"
  },
  {
    "recordingId": "395bfbbb-4b52-49bd-b7b1-9c20c3b8aaf2",
    "page": "48t",
    "bookSlug": "sh-1991",
    "url": "https://corksacredharp.bandcamp.com/track/48t-devotion-2",
    "embedUrl": "https://corksacredharp.bandcamp.com/track/48t-devotion-2",
    "status": "CONFIRMED"
  },
  {
    "recordingId": "395bfbbb-4b52-49bd-b7b1-9c20c3b8aaf2",
    "page": "29b",
    "bookSlug": "sh-1991",
    "url": "https://corksacredharp.bandcamp.com/track/29b-tribulation-3",
    "embedUrl": "https://corksacredharp.bandcamp.com/track/29b-tribulation-3",
    "status": "CONFIRMED"
  },
  {
    "recordingId": "395bfbbb-4b52-49bd-b7b1-9c20c3b8aaf2",
    "page": "49b",
    "bookSlug": "sh-1991",
    "url": "https://corksacredharp.bandcamp.com/track/49b-mear-9",
    "embedUrl": "https://corksacredharp.bandcamp.com/track/49b-mear-9",
    "status": "CONFIRMED"
  },
  {
    "recordingId": "395bfbbb-4b52-49bd-b7b1-9c20c3b8aaf2",
    "page": "39t",
    "bookSlug": "sh-1991",
    "url": "https://corksacredharp.bandcamp.com/track/39t-detroit-7",
    "embedUrl": "https://corksacredharp.bandcamp.com/track/39t-detroit-7",
    "status": "CONFIRMED"
  },
  {
    "recordingId": "395bfbbb-4b52-49bd-b7b1-9c20c3b8aaf2",
    "page": "138t",
    "bookSlug": "sh-1991",
    "url": "https://corksacredharp.bandcamp.com/track/138t-adoration-3",
    "embedUrl": "https://corksacredharp.bandcamp.com/track/138t-adoration-3",
    "status": "CONFIRMED"
  },
  {
    "recordingId": "395bfbbb-4b52-49bd-b7b1-9c20c3b8aaf2",
    "page": "297",
    "bookSlug": "sh-1991",
    "url": "https://corksacredharp.bandcamp.com/track/297-conversion",
    "embedUrl": "https://corksacredharp.bandcamp.com/track/297-conversion",
    "status": "CONFIRMED"
  },
  {
    "recordingId": "395bfbbb-4b52-49bd-b7b1-9c20c3b8aaf2",
    "page": "296",
    "bookSlug": "sh-1991",
    "url": "https://corksacredharp.bandcamp.com/track/296-sardinia-2",
    "embedUrl": "https://corksacredharp.bandcamp.com/track/296-sardinia-2",
    "status": "CONFIRMED"
  },
  {
    "recordingId": "395bfbbb-4b52-49bd-b7b1-9c20c3b8aaf2",
    "page": "88b",
    "bookSlug": "sh-1991",
    "url": "https://corksacredharp.bandcamp.com/track/88b-mount-zion-second-2",
    "embedUrl": "https://corksacredharp.bandcamp.com/track/88b-mount-zion-second-2",
    "status": "CONFIRMED"
  },
  {
    "recordingId": "395bfbbb-4b52-49bd-b7b1-9c20c3b8aaf2",
    "page": "545",
    "bookSlug": "sh-1991",
    "url": "https://corksacredharp.bandcamp.com/track/545-the-pilgrims-way-3",
    "embedUrl": "https://corksacredharp.bandcamp.com/track/545-the-pilgrims-way-3",
    "status": "CONFIRMED"
  },
  {
    "recordingId": "395bfbbb-4b52-49bd-b7b1-9c20c3b8aaf2",
    "page": "74b",
    "bookSlug": "sh-1991",
    "url": "https://corksacredharp.bandcamp.com/track/74b-king-of-peace-2",
    "embedUrl": "https://corksacredharp.bandcamp.com/track/74b-king-of-peace-2",
    "status": "CONFIRMED"
  },
  {
    "recordingId": "395bfbbb-4b52-49bd-b7b1-9c20c3b8aaf2",
    "page": "428",
    "bookSlug": "sh-1991",
    "url": "https://corksacredharp.bandcamp.com/track/428-world-unknown-5",
    "embedUrl": "https://corksacredharp.bandcamp.com/track/428-world-unknown-5",
    "status": "CONFIRMED"
  },
  {
    "recordingId": "395bfbbb-4b52-49bd-b7b1-9c20c3b8aaf2",
    "page": "50t",
    "bookSlug": "sh-1991",
    "url": "https://corksacredharp.bandcamp.com/track/50t-mortality",
    "embedUrl": "https://corksacredharp.bandcamp.com/track/50t-mortality",
    "status": "CONFIRMED"
  },
  {
    "recordingId": "395bfbbb-4b52-49bd-b7b1-9c20c3b8aaf2",
    "page": "123b",
    "bookSlug": "sh-1991",
    "url": "https://corksacredharp.bandcamp.com/track/123b-the-cross-of-christ",
    "embedUrl": "https://corksacredharp.bandcamp.com/track/123b-the-cross-of-christ",
    "status": "CONFIRMED"
  },
  {
    "recordingId": "395bfbbb-4b52-49bd-b7b1-9c20c3b8aaf2",
    "page": "77t",
    "bookSlug": "sh-1991",
    "url": "https://corksacredharp.bandcamp.com/track/77t-the-child-of-grace-9",
    "embedUrl": "https://corksacredharp.bandcamp.com/track/77t-the-child-of-grace-9",
    "status": "CONFIRMED"
  },
  {
    "recordingId": "395bfbbb-4b52-49bd-b7b1-9c20c3b8aaf2",
    "page": "110",
    "bookSlug": "sh-1991",
    "url": "https://corksacredharp.bandcamp.com/track/110-mount-vernon-2",
    "embedUrl": "https://corksacredharp.bandcamp.com/track/110-mount-vernon-2",
    "status": "CONFIRMED"
  },
  {
    "recordingId": "395bfbbb-4b52-49bd-b7b1-9c20c3b8aaf2",
    "page": "500",
    "bookSlug": "sh-1991",
    "url": "https://corksacredharp.bandcamp.com/track/500-living-hope-8",
    "embedUrl": "https://corksacredharp.bandcamp.com/track/500-living-hope-8",
    "status": "CONFIRMED"
  },
  {
    "recordingId": "395bfbbb-4b52-49bd-b7b1-9c20c3b8aaf2",
    "page": "176b",
    "bookSlug": "sh-1991",
    "url": "https://corksacredharp.bandcamp.com/track/176b-blooming-youth-3",
    "embedUrl": "https://corksacredharp.bandcamp.com/track/176b-blooming-youth-3",
    "status": "CONFIRMED"
  },
  {
    "recordingId": "395bfbbb-4b52-49bd-b7b1-9c20c3b8aaf2",
    "page": "567",
    "bookSlug": "sh-1991",
    "url": "https://corksacredharp.bandcamp.com/track/567-the-great-day-4",
    "embedUrl": "https://corksacredharp.bandcamp.com/track/567-the-great-day-4",
    "status": "CONFIRMED"
  },
  {
    "recordingId": "395bfbbb-4b52-49bd-b7b1-9c20c3b8aaf2",
    "page": "312b",
    "bookSlug": "sh-1991",
    "url": "https://corksacredharp.bandcamp.com/track/312b-restoration-first-5",
    "embedUrl": "https://corksacredharp.bandcamp.com/track/312b-restoration-first-5",
    "status": "CONFIRMED"
  },
  {
    "recordingId": "395bfbbb-4b52-49bd-b7b1-9c20c3b8aaf2",
    "page": "535",
    "bookSlug": "sh-1991",
    "url": "https://corksacredharp.bandcamp.com/track/535-shawmut-5",
    "embedUrl": "https://corksacredharp.bandcamp.com/track/535-shawmut-5",
    "status": "CONFIRMED"
  },
  {
    "recordingId": "395bfbbb-4b52-49bd-b7b1-9c20c3b8aaf2",
    "page": "481",
    "bookSlug": "sh-1991",
    "url": "https://corksacredharp.bandcamp.com/track/481-novakoski-8",
    "embedUrl": "https://corksacredharp.bandcamp.com/track/481-novakoski-8",
    "status": "CONFIRMED"
  },
  {
    "recordingId": "395bfbbb-4b52-49bd-b7b1-9c20c3b8aaf2",
    "page": "546",
    "bookSlug": "sh-1991",
    "url": "https://corksacredharp.bandcamp.com/track/546-my-brightest-days-4",
    "embedUrl": "https://corksacredharp.bandcamp.com/track/546-my-brightest-days-4",
    "status": "CONFIRMED"
  },
  {
    "recordingId": "395bfbbb-4b52-49bd-b7b1-9c20c3b8aaf2",
    "page": "100",
    "bookSlug": "sh-1991",
    "url": "https://corksacredharp.bandcamp.com/track/100-the-bower-of-prayer",
    "embedUrl": "https://corksacredharp.bandcamp.com/track/100-the-bower-of-prayer",
    "status": "CONFIRMED"
  },
  {
    "recordingId": "395bfbbb-4b52-49bd-b7b1-9c20c3b8aaf2",
    "page": "486",
    "bookSlug": "sh-1991",
    "url": "https://corksacredharp.bandcamp.com/track/486-beneficence-2",
    "embedUrl": "https://corksacredharp.bandcamp.com/track/486-beneficence-2",
    "status": "CONFIRMED"
  },
  {
    "recordingId": "395bfbbb-4b52-49bd-b7b1-9c20c3b8aaf2",
    "page": "436",
    "bookSlug": "sh-1991",
    "url": "https://corksacredharp.bandcamp.com/track/436-morning-sun-4",
    "embedUrl": "https://corksacredharp.bandcamp.com/track/436-morning-sun-4",
    "status": "CONFIRMED"
  },
  {
    "recordingId": "395bfbbb-4b52-49bd-b7b1-9c20c3b8aaf2",
    "page": "113",
    "bookSlug": "sh-1991",
    "url": "https://corksacredharp.bandcamp.com/track/113-the-prodigal-son-4",
    "embedUrl": "https://corksacredharp.bandcamp.com/track/113-the-prodigal-son-4",
    "status": "CONFIRMED"
  },
  {
    "recordingId": "395bfbbb-4b52-49bd-b7b1-9c20c3b8aaf2",
    "page": "501",
    "bookSlug": "sh-1991",
    "url": "https://corksacredharp.bandcamp.com/track/501-oleary-3",
    "embedUrl": "https://corksacredharp.bandcamp.com/track/501-oleary-3",
    "status": "CONFIRMED"
  },
  {
    "recordingId": "395bfbbb-4b52-49bd-b7b1-9c20c3b8aaf2",
    "page": "458",
    "bookSlug": "sh-1991",
    "url": "https://corksacredharp.bandcamp.com/track/458-friendship",
    "embedUrl": "https://corksacredharp.bandcamp.com/track/458-friendship",
    "status": "CONFIRMED"
  },
  {
    "recordingId": "395bfbbb-4b52-49bd-b7b1-9c20c3b8aaf2",
    "page": "430",
    "bookSlug": "sh-1991",
    "url": "https://corksacredharp.bandcamp.com/track/430-arbacoochee-7",
    "embedUrl": "https://corksacredharp.bandcamp.com/track/430-arbacoochee-7",
    "status": "CONFIRMED"
  },
  {
    "recordingId": "395bfbbb-4b52-49bd-b7b1-9c20c3b8aaf2",
    "page": "457",
    "bookSlug": "sh-1991",
    "url": "https://corksacredharp.bandcamp.com/track/457-wayfaring-stranger-3",
    "embedUrl": "https://corksacredharp.bandcamp.com/track/457-wayfaring-stranger-3",
    "status": "CONFIRMED"
  },
  {
    "recordingId": "395bfbbb-4b52-49bd-b7b1-9c20c3b8aaf2",
    "page": "135",
    "bookSlug": "sh-1991",
    "url": "https://corksacredharp.bandcamp.com/track/135-olney",
    "embedUrl": "https://corksacredharp.bandcamp.com/track/135-olney",
    "status": "CONFIRMED"
  },
  {
    "recordingId": "395bfbbb-4b52-49bd-b7b1-9c20c3b8aaf2",
    "page": "441",
    "bookSlug": "sh-1991",
    "url": "https://corksacredharp.bandcamp.com/track/441-raymond-4",
    "embedUrl": "https://corksacredharp.bandcamp.com/track/441-raymond-4",
    "status": "CONFIRMED"
  },
  {
    "recordingId": "395bfbbb-4b52-49bd-b7b1-9c20c3b8aaf2",
    "page": "503",
    "bookSlug": "sh-1991",
    "url": "https://corksacredharp.bandcamp.com/track/503-lloyd-5",
    "embedUrl": "https://corksacredharp.bandcamp.com/track/503-lloyd-5",
    "status": "CONFIRMED"
  },
  {
    "recordingId": "395bfbbb-4b52-49bd-b7b1-9c20c3b8aaf2",
    "page": "103",
    "bookSlug": "sh-1991",
    "url": "https://corksacredharp.bandcamp.com/track/103-animation",
    "embedUrl": "https://corksacredharp.bandcamp.com/track/103-animation",
    "status": "CONFIRMED"
  },
  {
    "recordingId": "395bfbbb-4b52-49bd-b7b1-9c20c3b8aaf2",
    "page": "159",
    "bookSlug": "sh-1991",
    "url": "https://corksacredharp.bandcamp.com/track/159-wondrous-love-3",
    "embedUrl": "https://corksacredharp.bandcamp.com/track/159-wondrous-love-3",
    "status": "CONFIRMED"
  },
  {
    "recordingId": "395bfbbb-4b52-49bd-b7b1-9c20c3b8aaf2",
    "page": "29t",
    "bookSlug": "sh-1991",
    "url": "https://corksacredharp.bandcamp.com/track/29t-fairfield-6",
    "embedUrl": "https://corksacredharp.bandcamp.com/track/29t-fairfield-6",
    "status": "CONFIRMED"
  },
  {
    "recordingId": "395bfbbb-4b52-49bd-b7b1-9c20c3b8aaf2",
    "page": "42",
    "bookSlug": "sh-1991",
    "url": "https://corksacredharp.bandcamp.com/track/42-clamanda-6",
    "embedUrl": "https://corksacredharp.bandcamp.com/track/42-clamanda-6",
    "status": "CONFIRMED"
  },
  {
    "recordingId": "395bfbbb-4b52-49bd-b7b1-9c20c3b8aaf2",
    "page": "111b",
    "bookSlug": "sh-1991",
    "url": "https://corksacredharp.bandcamp.com/track/111b-to-die-no-more-4",
    "embedUrl": "https://corksacredharp.bandcamp.com/track/111b-to-die-no-more-4",
    "status": "CONFIRMED"
  },
  {
    "recordingId": "395bfbbb-4b52-49bd-b7b1-9c20c3b8aaf2",
    "page": "192",
    "bookSlug": "sh-1991",
    "url": "https://corksacredharp.bandcamp.com/track/192-schenectady-7",
    "embedUrl": "https://corksacredharp.bandcamp.com/track/192-schenectady-7",
    "status": "CONFIRMED"
  },
  {
    "recordingId": "395bfbbb-4b52-49bd-b7b1-9c20c3b8aaf2",
    "page": "201",
    "bookSlug": "sh-1991",
    "url": "https://corksacredharp.bandcamp.com/track/201-pilgrim-4",
    "embedUrl": "https://corksacredharp.bandcamp.com/track/201-pilgrim-4",
    "status": "CONFIRMED"
  },
  {
    "recordingId": "395bfbbb-4b52-49bd-b7b1-9c20c3b8aaf2",
    "page": "283",
    "bookSlug": "sh-1991",
    "url": "https://corksacredharp.bandcamp.com/track/283-sabbath-morning-5",
    "embedUrl": "https://corksacredharp.bandcamp.com/track/283-sabbath-morning-5",
    "status": "CONFIRMED"
  },
  {
    "recordingId": "395bfbbb-4b52-49bd-b7b1-9c20c3b8aaf2",
    "page": "460",
    "bookSlug": "sh-1991",
    "url": "https://corksacredharp.bandcamp.com/track/460-sardis-5",
    "embedUrl": "https://corksacredharp.bandcamp.com/track/460-sardis-5",
    "status": "CONFIRMED"
  },
  {
    "recordingId": "395bfbbb-4b52-49bd-b7b1-9c20c3b8aaf2",
    "page": "90",
    "bookSlug": "sh-1991",
    "url": "https://corksacredharp.bandcamp.com/track/90-look-out",
    "embedUrl": "https://corksacredharp.bandcamp.com/track/90-look-out",
    "status": "CONFIRMED"
  },
  {
    "recordingId": "395bfbbb-4b52-49bd-b7b1-9c20c3b8aaf2",
    "page": "270",
    "bookSlug": "sh-1991",
    "url": "https://corksacredharp.bandcamp.com/track/270-confidence-8",
    "embedUrl": "https://corksacredharp.bandcamp.com/track/270-confidence-8",
    "status": "CONFIRMED"
  },
  {
    "recordingId": "395bfbbb-4b52-49bd-b7b1-9c20c3b8aaf2",
    "page": "405",
    "bookSlug": "sh-1991",
    "url": "https://corksacredharp.bandcamp.com/track/405-the-marcellas",
    "embedUrl": "https://corksacredharp.bandcamp.com/track/405-the-marcellas",
    "status": "CONFIRMED"
  },
  {
    "recordingId": "395bfbbb-4b52-49bd-b7b1-9c20c3b8aaf2",
    "page": "475",
    "bookSlug": "sh-1991",
    "url": "https://corksacredharp.bandcamp.com/track/475-a-thankful-heart-5",
    "embedUrl": "https://corksacredharp.bandcamp.com/track/475-a-thankful-heart-5",
    "status": "CONFIRMED"
  },
  {
    "recordingId": "395bfbbb-4b52-49bd-b7b1-9c20c3b8aaf2",
    "page": "189",
    "bookSlug": "sh-1991",
    "url": "https://corksacredharp.bandcamp.com/track/189-montgomery-5",
    "embedUrl": "https://corksacredharp.bandcamp.com/track/189-montgomery-5",
    "status": "CONFIRMED"
  },
  {
    "recordingId": "395bfbbb-4b52-49bd-b7b1-9c20c3b8aaf2",
    "page": "426b",
    "bookSlug": "sh-1991",
    "url": "https://corksacredharp.bandcamp.com/track/426b-jasper-4",
    "embedUrl": "https://corksacredharp.bandcamp.com/track/426b-jasper-4",
    "status": "CONFIRMED"
  },
  {
    "recordingId": "395bfbbb-4b52-49bd-b7b1-9c20c3b8aaf2",
    "page": "188",
    "bookSlug": "sh-1991",
    "url": "https://corksacredharp.bandcamp.com/track/188-spring",
    "embedUrl": "https://corksacredharp.bandcamp.com/track/188-spring",
    "status": "CONFIRMED"
  },
  {
    "recordingId": "395bfbbb-4b52-49bd-b7b1-9c20c3b8aaf2",
    "page": "384",
    "bookSlug": "sh-1991",
    "url": "https://corksacredharp.bandcamp.com/track/384-panting-for-heaven-5",
    "embedUrl": "https://corksacredharp.bandcamp.com/track/384-panting-for-heaven-5",
    "status": "CONFIRMED"
  },
  {
    "recordingId": "395bfbbb-4b52-49bd-b7b1-9c20c3b8aaf2",
    "page": "67",
    "bookSlug": "sh-1991",
    "url": "https://corksacredharp.bandcamp.com/track/67-columbus-3",
    "embedUrl": "https://corksacredharp.bandcamp.com/track/67-columbus-3",
    "status": "CONFIRMED"
  },
  {
    "recordingId": "395bfbbb-4b52-49bd-b7b1-9c20c3b8aaf2",
    "page": "272",
    "bookSlug": "sh-1991",
    "url": "https://corksacredharp.bandcamp.com/track/272-exhortation-second-8",
    "embedUrl": "https://corksacredharp.bandcamp.com/track/272-exhortation-second-8",
    "status": "CONFIRMED"
  },
  {
    "recordingId": "395bfbbb-4b52-49bd-b7b1-9c20c3b8aaf2",
    "page": "542",
    "bookSlug": "sh-1991",
    "url": "https://corksacredharp.bandcamp.com/track/542-ill-seek-his-blessings-7",
    "embedUrl": "https://corksacredharp.bandcamp.com/track/542-ill-seek-his-blessings-7",
    "status": "CONFIRMED"
  },
  {
    "recordingId": "395bfbbb-4b52-49bd-b7b1-9c20c3b8aaf2",
    "page": "279",
    "bookSlug": "sh-1991",
    "url": "https://corksacredharp.bandcamp.com/track/279-the-shepherds-flock-2",
    "embedUrl": "https://corksacredharp.bandcamp.com/track/279-the-shepherds-flock-2",
    "status": "CONFIRMED"
  },
  {
    "recordingId": "395bfbbb-4b52-49bd-b7b1-9c20c3b8aaf2",
    "page": "208",
    "bookSlug": "sh-1991",
    "url": "https://corksacredharp.bandcamp.com/track/208-traveling-on-2",
    "embedUrl": "https://corksacredharp.bandcamp.com/track/208-traveling-on-2",
    "status": "CONFIRMED"
  },
  {
    "recordingId": "395bfbbb-4b52-49bd-b7b1-9c20c3b8aaf2",
    "page": "133",
    "bookSlug": "sh-1991",
    "url": "https://corksacredharp.bandcamp.com/track/133-hebrew-children-4",
    "embedUrl": "https://corksacredharp.bandcamp.com/track/133-hebrew-children-4",
    "status": "CONFIRMED"
  },
  {
    "recordingId": "395bfbbb-4b52-49bd-b7b1-9c20c3b8aaf2",
    "page": "377",
    "bookSlug": "sh-1991",
    "url": "https://corksacredharp.bandcamp.com/track/377-eternal-praise-7",
    "embedUrl": "https://corksacredharp.bandcamp.com/track/377-eternal-praise-7",
    "status": "CONFIRMED"
  },
  {
    "recordingId": "395bfbbb-4b52-49bd-b7b1-9c20c3b8aaf2",
    "page": "348t",
    "bookSlug": "sh-1991",
    "url": "https://corksacredharp.bandcamp.com/track/348t-ainslie-5",
    "embedUrl": "https://corksacredharp.bandcamp.com/track/348t-ainslie-5",
    "status": "CONFIRMED"
  },
  {
    "recordingId": "395bfbbb-4b52-49bd-b7b1-9c20c3b8aaf2",
    "page": "349",
    "bookSlug": "sh-1991",
    "url": "https://corksacredharp.bandcamp.com/track/349-a-cross-for-me",
    "embedUrl": "https://corksacredharp.bandcamp.com/track/349-a-cross-for-me",
    "status": "CONFIRMED"
  },
  {
    "recordingId": "395bfbbb-4b52-49bd-b7b1-9c20c3b8aaf2",
    "page": "114",
    "bookSlug": "sh-1991",
    "url": "https://corksacredharp.bandcamp.com/track/114-saints-delight-5",
    "embedUrl": "https://corksacredharp.bandcamp.com/track/114-saints-delight-5",
    "status": "CONFIRMED"
  },
  {
    "recordingId": "395bfbbb-4b52-49bd-b7b1-9c20c3b8aaf2",
    "page": "228",
    "bookSlug": "sh-1991",
    "url": "https://corksacredharp.bandcamp.com/track/228-marlborough-8",
    "embedUrl": "https://corksacredharp.bandcamp.com/track/228-marlborough-8",
    "status": "CONFIRMED"
  },
  {
    "recordingId": "395bfbbb-4b52-49bd-b7b1-9c20c3b8aaf2",
    "page": "556",
    "bookSlug": "sh-1991",
    "url": "https://corksacredharp.bandcamp.com/track/556-portland-6",
    "embedUrl": "https://corksacredharp.bandcamp.com/track/556-portland-6",
    "status": "CONFIRMED"
  },
  {
    "recordingId": "395bfbbb-4b52-49bd-b7b1-9c20c3b8aaf2",
    "page": "187",
    "bookSlug": "sh-1991",
    "url": "https://corksacredharp.bandcamp.com/track/187-protection-first-5",
    "embedUrl": "https://corksacredharp.bandcamp.com/track/187-protection-first-5",
    "status": "CONFIRMED"
  },
  {
    "recordingId": "395bfbbb-4b52-49bd-b7b1-9c20c3b8aaf2",
    "page": "84",
    "bookSlug": "sh-1991",
    "url": "https://corksacredharp.bandcamp.com/track/84-amsterdam-7",
    "embedUrl": "https://corksacredharp.bandcamp.com/track/84-amsterdam-7",
    "status": "CONFIRMED"
  },
  {
    "recordingId": "395bfbbb-4b52-49bd-b7b1-9c20c3b8aaf2",
    "page": "196",
    "bookSlug": "sh-1991",
    "url": "https://corksacredharp.bandcamp.com/track/196-alabama-4",
    "embedUrl": "https://corksacredharp.bandcamp.com/track/196-alabama-4",
    "status": "CONFIRMED"
  },
  {
    "recordingId": "395bfbbb-4b52-49bd-b7b1-9c20c3b8aaf2",
    "page": "319",
    "bookSlug": "sh-1991",
    "url": "https://corksacredharp.bandcamp.com/track/319-religion-is-a-fortune-4",
    "embedUrl": "https://corksacredharp.bandcamp.com/track/319-religion-is-a-fortune-4",
    "status": "CONFIRMED"
  },
  {
    "recordingId": "395bfbbb-4b52-49bd-b7b1-9c20c3b8aaf2",
    "page": "392",
    "bookSlug": "sh-1991",
    "url": "https://corksacredharp.bandcamp.com/track/392-manchester-3",
    "embedUrl": "https://corksacredharp.bandcamp.com/track/392-manchester-3",
    "status": "CONFIRMED"
  },
  {
    "recordingId": "395bfbbb-4b52-49bd-b7b1-9c20c3b8aaf2",
    "page": "454",
    "bookSlug": "sh-1991",
    "url": "https://corksacredharp.bandcamp.com/track/454-the-better-land-7",
    "embedUrl": "https://corksacredharp.bandcamp.com/track/454-the-better-land-7",
    "status": "CONFIRMED"
  },
  {
    "recordingId": "395bfbbb-4b52-49bd-b7b1-9c20c3b8aaf2",
    "page": "350",
    "bookSlug": "sh-1991",
    "url": "https://corksacredharp.bandcamp.com/track/350-nativity-3",
    "embedUrl": "https://corksacredharp.bandcamp.com/track/350-nativity-3",
    "status": "CONFIRMED"
  },
  {
    "recordingId": "395bfbbb-4b52-49bd-b7b1-9c20c3b8aaf2",
    "page": "513",
    "bookSlug": "sh-1991",
    "url": "https://corksacredharp.bandcamp.com/track/513-joyful-2",
    "embedUrl": "https://corksacredharp.bandcamp.com/track/513-joyful-2",
    "status": "CONFIRMED"
  },
  {
    "recordingId": "395bfbbb-4b52-49bd-b7b1-9c20c3b8aaf2",
    "page": "278b",
    "bookSlug": "sh-1991",
    "url": "https://corksacredharp.bandcamp.com/track/278b-traveling-pilgrim",
    "embedUrl": "https://corksacredharp.bandcamp.com/track/278b-traveling-pilgrim",
    "status": "CONFIRMED"
  },
  {
    "recordingId": "395bfbbb-4b52-49bd-b7b1-9c20c3b8aaf2",
    "page": "504",
    "bookSlug": "sh-1991",
    "url": "https://corksacredharp.bandcamp.com/track/504-wood-street-6",
    "embedUrl": "https://corksacredharp.bandcamp.com/track/504-wood-street-6",
    "status": "CONFIRMED"
  },
  {
    "recordingId": "395bfbbb-4b52-49bd-b7b1-9c20c3b8aaf2",
    "page": "179",
    "bookSlug": "sh-1991",
    "url": "https://corksacredharp.bandcamp.com/track/179-the-christian-warfare-5",
    "embedUrl": "https://corksacredharp.bandcamp.com/track/179-the-christian-warfare-5",
    "status": "CONFIRMED"
  },
  {
    "recordingId": "395bfbbb-4b52-49bd-b7b1-9c20c3b8aaf2",
    "page": "410t",
    "bookSlug": "sh-1991",
    "url": "https://corksacredharp.bandcamp.com/track/410t-the-dying-californian-2",
    "embedUrl": "https://corksacredharp.bandcamp.com/track/410t-the-dying-californian-2",
    "status": "CONFIRMED"
  },
  {
    "recordingId": "395bfbbb-4b52-49bd-b7b1-9c20c3b8aaf2",
    "page": "278t",
    "bookSlug": "sh-1991",
    "url": "https://corksacredharp.bandcamp.com/track/278t-love-shall-never-die-5",
    "embedUrl": "https://corksacredharp.bandcamp.com/track/278t-love-shall-never-die-5",
    "status": "CONFIRMED"
  },
  {
    "recordingId": "395bfbbb-4b52-49bd-b7b1-9c20c3b8aaf2",
    "page": "209",
    "bookSlug": "sh-1991",
    "url": "https://corksacredharp.bandcamp.com/track/209-evening-shade-8",
    "embedUrl": "https://corksacredharp.bandcamp.com/track/209-evening-shade-8",
    "status": "CONFIRMED"
  },
  {
    "recordingId": "395bfbbb-4b52-49bd-b7b1-9c20c3b8aaf2",
    "page": "210",
    "bookSlug": "sh-1991",
    "url": "https://corksacredharp.bandcamp.com/track/210-lena-3",
    "embedUrl": "https://corksacredharp.bandcamp.com/track/210-lena-3",
    "status": "CONFIRMED"
  },
  {
    "recordingId": "395bfbbb-4b52-49bd-b7b1-9c20c3b8aaf2",
    "page": "49t",
    "bookSlug": "sh-1991",
    "url": "https://corksacredharp.bandcamp.com/track/49t-old-hundred-7",
    "embedUrl": "https://corksacredharp.bandcamp.com/track/49t-old-hundred-7",
    "status": "CONFIRMED"
  },
  {
    "recordingId": "395bfbbb-4b52-49bd-b7b1-9c20c3b8aaf2",
    "page": "271b",
    "bookSlug": "sh-1991",
    "url": "https://corksacredharp.bandcamp.com/track/271b-restoration-second",
    "embedUrl": "https://corksacredharp.bandcamp.com/track/271b-restoration-second",
    "status": "CONFIRMED"
  },
  {
    "recordingId": "395bfbbb-4b52-49bd-b7b1-9c20c3b8aaf2",
    "page": "565",
    "bookSlug": "sh-1991",
    "url": "https://corksacredharp.bandcamp.com/track/565-the-hill-of-zion-4",
    "embedUrl": "https://corksacredharp.bandcamp.com/track/565-the-hill-of-zion-4",
    "status": "CONFIRMED"
  },
  {
    "recordingId": "395bfbbb-4b52-49bd-b7b1-9c20c3b8aaf2",
    "page": "86",
    "bookSlug": "sh-1991",
    "url": "https://corksacredharp.bandcamp.com/track/86-poland-6",
    "embedUrl": "https://corksacredharp.bandcamp.com/track/86-poland-6",
    "status": "CONFIRMED"
  },
  {
    "recordingId": "395bfbbb-4b52-49bd-b7b1-9c20c3b8aaf2",
    "page": "65",
    "bookSlug": "sh-1991",
    "url": "https://corksacredharp.bandcamp.com/track/65-sweet-prospect-5",
    "embedUrl": "https://corksacredharp.bandcamp.com/track/65-sweet-prospect-5",
    "status": "CONFIRMED"
  },
  {
    "recordingId": "395bfbbb-4b52-49bd-b7b1-9c20c3b8aaf2",
    "page": "181",
    "bookSlug": "sh-1991",
    "url": "https://corksacredharp.bandcamp.com/track/181-exit-4",
    "embedUrl": "https://corksacredharp.bandcamp.com/track/181-exit-4",
    "status": "CONFIRMED"
  },
  {
    "recordingId": "395bfbbb-4b52-49bd-b7b1-9c20c3b8aaf2",
    "page": "318",
    "bookSlug": "sh-1991",
    "url": "https://corksacredharp.bandcamp.com/track/318-present-joys-7",
    "embedUrl": "https://corksacredharp.bandcamp.com/track/318-present-joys-7",
    "status": "CONFIRMED"
  },
  {
    "recordingId": "395bfbbb-4b52-49bd-b7b1-9c20c3b8aaf2",
    "page": "335",
    "bookSlug": "sh-1991",
    "url": "https://corksacredharp.bandcamp.com/track/335-return-again-10",
    "embedUrl": "https://corksacredharp.bandcamp.com/track/335-return-again-10",
    "status": "CONFIRMED"
  },
  {
    "recordingId": "395bfbbb-4b52-49bd-b7b1-9c20c3b8aaf2",
    "page": "102",
    "bookSlug": "sh-1991",
    "url": "https://corksacredharp.bandcamp.com/track/102-fulfillment-5",
    "embedUrl": "https://corksacredharp.bandcamp.com/track/102-fulfillment-5",
    "status": "CONFIRMED"
  },
  {
    "recordingId": "395bfbbb-4b52-49bd-b7b1-9c20c3b8aaf2",
    "page": "32t",
    "bookSlug": "sh-1991",
    "url": "https://corksacredharp.bandcamp.com/track/32t-corinth-6",
    "embedUrl": "https://corksacredharp.bandcamp.com/track/32t-corinth-6",
    "status": "CONFIRMED"
  },
  {
    "recordingId": "395bfbbb-4b52-49bd-b7b1-9c20c3b8aaf2",
    "page": "163b",
    "bookSlug": "sh-1991",
    "url": "https://corksacredharp.bandcamp.com/track/163b-china-6",
    "embedUrl": "https://corksacredharp.bandcamp.com/track/163b-china-6",
    "status": "CONFIRMED"
  },
  {
    "recordingId": "395bfbbb-4b52-49bd-b7b1-9c20c3b8aaf2",
    "page": "148",
    "bookSlug": "sh-1991",
    "url": "https://corksacredharp.bandcamp.com/track/148-jefferson-7",
    "embedUrl": "https://corksacredharp.bandcamp.com/track/148-jefferson-7",
    "status": "CONFIRMED"
  },
  {
    "recordingId": "395bfbbb-4b52-49bd-b7b1-9c20c3b8aaf2",
    "page": "108b",
    "bookSlug": "sh-1991",
    "url": "https://corksacredharp.bandcamp.com/track/108b-the-traveler-2",
    "embedUrl": "https://corksacredharp.bandcamp.com/track/108b-the-traveler-2",
    "status": "CONFIRMED"
  },
  {
    "recordingId": "395bfbbb-4b52-49bd-b7b1-9c20c3b8aaf2",
    "page": "55",
    "bookSlug": "sh-1991",
    "url": "https://corksacredharp.bandcamp.com/track/55-sisters-farewell",
    "embedUrl": "https://corksacredharp.bandcamp.com/track/55-sisters-farewell",
    "status": "CONFIRMED"
  },
  {
    "recordingId": "395bfbbb-4b52-49bd-b7b1-9c20c3b8aaf2",
    "page": "373",
    "bookSlug": "sh-1991",
    "url": "https://corksacredharp.bandcamp.com/track/373-homeward-bound-2",
    "embedUrl": "https://corksacredharp.bandcamp.com/track/373-homeward-bound-2",
    "status": "CONFIRMED"
  },
  {
    "recordingId": "395bfbbb-4b52-49bd-b7b1-9c20c3b8aaf2",
    "page": "82t",
    "bookSlug": "sh-1991",
    "url": "https://corksacredharp.bandcamp.com/track/82t-bound-for-canaan-5",
    "embedUrl": "https://corksacredharp.bandcamp.com/track/82t-bound-for-canaan-5",
    "status": "CONFIRMED"
  },
  {
    "recordingId": "395bfbbb-4b52-49bd-b7b1-9c20c3b8aaf2",
    "page": "112",
    "bookSlug": "sh-1991",
    "url": "https://corksacredharp.bandcamp.com/track/112-the-last-words-of-copernicus-7",
    "embedUrl": "https://corksacredharp.bandcamp.com/track/112-the-last-words-of-copernicus-7",
    "status": "CONFIRMED"
  },
  {
    "recordingId": "395bfbbb-4b52-49bd-b7b1-9c20c3b8aaf2",
    "page": "472",
    "bookSlug": "sh-1991",
    "url": "https://corksacredharp.bandcamp.com/track/472-akin-8",
    "embedUrl": "https://corksacredharp.bandcamp.com/track/472-akin-8",
    "status": "CONFIRMED"
  }
]