[
  {
    "recordingId": "9bcc63c8-77c7-4e0e-aa5b-cc7c1d5085a4",
    "page": "112",
    "bookSlug": "sh-1936",
    "url": "https://www.youtube.com/watch?v=U9N8JoLlLh4&t=0",
    "embedUrl": "https://youtube.com/embed/U9N8JoLlLh4?amp;start=0",
    "status": "CONFIRMED"
  },
  {
    "recordingId": "9bcc63c8-77c7-4e0e-aa5b-cc7c1d5085a4",
    "page": "408",
    "bookSlug": "sh-1936",
    "url": "https://www.youtube.com/watch?v=U9N8JoLlLh4&t=72",
    "embedUrl": "https://youtube.com/embed/U9N8JoLlLh4?amp;start=72",
    "status": "CONFIRMED"
  },
  {
    "recordingId": "9bcc63c8-77c7-4e0e-aa5b-cc7c1d5085a4",
    "page": "430",
    "bookSlug": "sh-1936",
    "url": "https://www.youtube.com/watch?v=U9N8JoLlLh4&t=190",
    "embedUrl": "https://youtube.com/embed/U9N8JoLlLh4?amp;start=190",
    "status": "CONFIRMED"
  },
  {
    "recordingId": "9bcc63c8-77c7-4e0e-aa5b-cc7c1d5085a4",
    "page": "212",
    "bookSlug": "sh-1936",
    "url": "https://www.youtube.com/watch?v=U9N8JoLlLh4&t=313",
    "embedUrl": "https://youtube.com/embed/U9N8JoLlLh4?amp;start=313",
    "status": "CONFIRMED"
  },
  {
    "recordingId": "9bcc63c8-77c7-4e0e-aa5b-cc7c1d5085a4",
    "page": "211",
    "bookSlug": "sh-1936",
    "url": "https://www.youtube.com/watch?v=U9N8JoLlLh4&t=454",
    "embedUrl": "https://youtube.com/embed/U9N8JoLlLh4?amp;start=454",
    "status": "CONFIRMED"
  },
  {
    "recordingId": "9bcc63c8-77c7-4e0e-aa5b-cc7c1d5085a4",
    "page": "428",
    "bookSlug": "sh-1936",
    "url": "https://www.youtube.com/watch?v=U9N8JoLlLh4&t=613",
    "embedUrl": "https://youtube.com/embed/U9N8JoLlLh4?amp;start=613",
    "status": "CONFIRMED"
  },
  {
    "recordingId": "9bcc63c8-77c7-4e0e-aa5b-cc7c1d5085a4",
    "page": "186",
    "bookSlug": "sh-1936",
    "url": "https://www.youtube.com/watch?v=U9N8JoLlLh4&t=747",
    "embedUrl": "https://youtube.com/embed/U9N8JoLlLh4?amp;start=747",
    "status": "CONFIRMED"
  },
  {
    "recordingId": "9bcc63c8-77c7-4e0e-aa5b-cc7c1d5085a4",
    "page": "110",
    "bookSlug": "sh-1936",
    "url": "https://www.youtube.com/watch?v=U9N8JoLlLh4&t=864",
    "embedUrl": "https://youtube.com/embed/U9N8JoLlLh4?amp;start=864",
    "status": "CONFIRMED"
  },
  {
    "recordingId": "9bcc63c8-77c7-4e0e-aa5b-cc7c1d5085a4",
    "page": "138t",
    "bookSlug": "sh-1936",
    "url": "https://www.youtube.com/watch?v=U9N8JoLlLh4&t=995",
    "embedUrl": "https://youtube.com/embed/U9N8JoLlLh4?amp;start=995",
    "status": "CONFIRMED"
  },
  {
    "recordingId": "9bcc63c8-77c7-4e0e-aa5b-cc7c1d5085a4",
    "page": "217",
    "bookSlug": "sh-1936",
    "url": "https://www.youtube.com/watch?v=U9N8JoLlLh4&t=1100",
    "embedUrl": "https://youtube.com/embed/U9N8JoLlLh4?amp;start=1100",
    "status": "CONFIRMED"
  },
  {
    "recordingId": "9bcc63c8-77c7-4e0e-aa5b-cc7c1d5085a4",
    "page": "298",
    "bookSlug": "sh-1936",
    "url": "https://www.youtube.com/watch?v=U9N8JoLlLh4&t=1228",
    "embedUrl": "https://youtube.com/embed/U9N8JoLlLh4?amp;start=1228",
    "status": "CONFIRMED"
  },
  {
    "recordingId": "9bcc63c8-77c7-4e0e-aa5b-cc7c1d5085a4",
    "page": "200",
    "bookSlug": "sh-1936",
    "url": "https://www.youtube.com/watch?v=U9N8JoLlLh4&t=1351",
    "embedUrl": "https://youtube.com/embed/U9N8JoLlLh4?amp;start=1351",
    "status": "CONFIRMED"
  },
  {
    "recordingId": "9bcc63c8-77c7-4e0e-aa5b-cc7c1d5085a4",
    "page": "197",
    "bookSlug": "sh-1936",
    "url": "https://www.youtube.com/watch?v=U9N8JoLlLh4&t=1501",
    "embedUrl": "https://youtube.com/embed/U9N8JoLlLh4?amp;start=1501",
    "status": "CONFIRMED"
  },
  {
    "recordingId": "9bcc63c8-77c7-4e0e-aa5b-cc7c1d5085a4",
    "page": "377",
    "bookSlug": "sh-1936",
    "url": "https://www.youtube.com/watch?v=U9N8JoLlLh4&t=1624",
    "embedUrl": "https://youtube.com/embed/U9N8JoLlLh4?amp;start=1624",
    "status": "CONFIRMED"
  },
  {
    "recordingId": "9bcc63c8-77c7-4e0e-aa5b-cc7c1d5085a4",
    "page": "299",
    "bookSlug": "sh-1936",
    "url": "https://www.youtube.com/watch?v=U9N8JoLlLh4&t=1781",
    "embedUrl": "https://youtube.com/embed/U9N8JoLlLh4?amp;start=1781",
    "status": "CONFIRMED"
  },
  {
    "recordingId": "9bcc63c8-77c7-4e0e-aa5b-cc7c1d5085a4",
    "page": "454",
    "bookSlug": "sh-1936",
    "url": "https://www.youtube.com/watch?v=U9N8JoLlLh4&t=1893",
    "embedUrl": "https://youtube.com/embed/U9N8JoLlLh4?amp;start=1893",
    "status": "CONFIRMED"
  },
  {
    "recordingId": "9bcc63c8-77c7-4e0e-aa5b-cc7c1d5085a4",
    "page": "272",
    "bookSlug": "sh-1936",
    "url": "https://www.youtube.com/watch?v=U9N8JoLlLh4&t=2018",
    "embedUrl": "https://youtube.com/embed/U9N8JoLlLh4?amp;start=2018",
    "status": "CONFIRMED"
  },
  {
    "recordingId": "9bcc63c8-77c7-4e0e-aa5b-cc7c1d5085a4",
    "page": "187",
    "bookSlug": "sh-1936",
    "url": "https://www.youtube.com/watch?v=U9N8JoLlLh4&t=2156",
    "embedUrl": "https://youtube.com/embed/U9N8JoLlLh4?amp;start=2156",
    "status": "CONFIRMED"
  },
  {
    "recordingId": "9bcc63c8-77c7-4e0e-aa5b-cc7c1d5085a4",
    "page": "198",
    "bookSlug": "sh-1936",
    "url": "https://www.youtube.com/watch?v=U9N8JoLlLh4&t=2267",
    "embedUrl": "https://youtube.com/embed/U9N8JoLlLh4?amp;start=2267",
    "status": "CONFIRMED"
  },
  {
    "recordingId": "9bcc63c8-77c7-4e0e-aa5b-cc7c1d5085a4",
    "page": "380",
    "bookSlug": "sh-1936",
    "url": "https://www.youtube.com/watch?v=U9N8JoLlLh4&t=2441",
    "embedUrl": "https://youtube.com/embed/U9N8JoLlLh4?amp;start=2441",
    "status": "CONFIRMED"
  },
  {
    "recordingId": "9bcc63c8-77c7-4e0e-aa5b-cc7c1d5085a4",
    "page": "361",
    "bookSlug": "sh-1936",
    "url": "https://www.youtube.com/watch?v=U9N8JoLlLh4&t=2604",
    "embedUrl": "https://youtube.com/embed/U9N8JoLlLh4?amp;start=2604",
    "status": "CONFIRMED"
  },
  {
    "recordingId": "9bcc63c8-77c7-4e0e-aa5b-cc7c1d5085a4",
    "page": "362",
    "bookSlug": "sh-1936",
    "url": "https://www.youtube.com/watch?v=U9N8JoLlLh4&t=2768",
    "embedUrl": "https://youtube.com/embed/U9N8JoLlLh4?amp;start=2768",
    "status": "CONFIRMED"
  }
]
